{
  "experiment": "greedy_stacking_adapters",
  "timestamp": "2026-03-15T21:25:49.500724",
  "baseline": 0.5343899465628633,
  "scores": [
    0.5343899465628633,
    0.5778815390931689,
    0.6127456529099885,
    0.7235907874436635,
    0.6218226578799663,
    0.5507771037897513
  ],
  "blocks": [
    [
      16,
      17
    ],
    [
      2,
      3
    ],
    [
      4,
      5
    ],
    [
      12,
      13
    ],
    [
      10,
      11
    ]
  ],
  "iterations": [
    {
      "iteration": 1,
      "evaluations": [
        {
          "block": [
            2,
            3
          ],
          "score": 0.5350129065761265,
          "delta": 0.0006229600132632296,
          "displacement_rho": 0.1723741665482521
        },
        {
          "block": [
            16,
            17
          ],
          "score": 0.5778815390931689,
          "delta": 0.043491592530305545,
          "displacement_rho": 0.19587132427841425
        },
        {
          "block": [
            14,
            15
          ],
          "score": 0.27418149847994394,
          "delta": -0.2602084480829194,
          "displacement_rho": 0.20631681010127068
        }
      ],
      "best_block": [
        16,
        17
      ],
      "best_score": 0.5778815390931689,
      "improved": true,
      "delta": 0.043491592530305545
    },
    {
      "iteration": 2,
      "evaluations": [
        {
          "block": [
            2,
            3
          ],
          "score": 0.6127456529099885,
          "delta": 0.03486411381681964,
          "displacement_rho": 0.24625017121434212
        },
        {
          "block": [
            12,
            13
          ],
          "score": 0.45591494750394945,
          "delta": -0.12196659158921941,
          "displacement_rho": 0.28467072546482086
        },
        {
          "block": [
            14,
            15
          ],
          "score": 0.37338184322426754,
          "delta": -0.20449969586890132,
          "displacement_rho": 0.3016655705869198
        }
      ],
      "best_block": [
        2,
        3
      ],
      "best_score": 0.6127456529099885,
      "improved": true,
      "delta": 0.03486411381681964
    },
    {
      "iteration": 3,
      "evaluations": [
        {
          "block": [
            4,
            5
          ],
          "score": 0.7235907874436635,
          "delta": 0.11084513453367495,
          "displacement_rho": 0.22145750001072884
        },
        {
          "block": [
            6,
            7
          ],
          "score": 0.5800044529447484,
          "delta": -0.03274119996524005,
          "displacement_rho": 0.23303310200572014
        },
        {
          "block": [
            14,
            15
          ],
          "score": 0.6478605888753473,
          "delta": 0.03511493596535875,
          "displacement_rho": 0.2942439243197441
        }
      ],
      "best_block": [
        4,
        5
      ],
      "best_score": 0.7235907874436635,
      "improved": true,
      "delta": 0.11084513453367495
    },
    {
      "iteration": 4,
      "evaluations": [
        {
          "block": [
            10,
            11
          ],
          "score": 0.5994205176242686,
          "delta": -0.12417026981939483,
          "displacement_rho": 0.2291894070804119
        },
        {
          "block": [
            12,
            13
          ],
          "score": 0.6218226578799663,
          "delta": -0.10176812956369718,
          "displacement_rho": 0.2599932551383972
        },
        {
          "block": [
            14,
            15
          ],
          "score": 0.6158241003986178,
          "delta": -0.10776668704504566,
          "displacement_rho": 0.2614949010312557
        }
      ],
      "best_block": [
        12,
        13
      ],
      "best_score": 0.6218226578799663,
      "improved": false,
      "delta": -0.10176812956369718
    },
    {
      "iteration": 5,
      "evaluations": [
        {
          "block": [
            18,
            19
          ],
          "score": 0.533044216079208,
          "delta": -0.08877844180075822,
          "displacement_rho": 0.17603353969752789
        },
        {
          "block": [
            10,
            11
          ],
          "score": 0.5507771037897513,
          "delta": -0.07104555409021496,
          "displacement_rho": 0.1767106093466282
        },
        {
          "block": [
            14,
            15
          ],
          "score": 0.5063640248068793,
          "delta": -0.11545863307308701,
          "displacement_rho": 0.19405508041381836
        }
      ],
      "best_block": [
        10,
        11
      ],
      "best_score": 0.5507771037897513,
      "improved": false,
      "delta": -0.07104555409021496
    }
  ],
  "adapter_bottleneck": 256,
  "adapter_train_steps": 50,
  "train_adapters": true
}